[
  {
    "line_index_1": 61,
    "line_index_2": 41,
    "heRef_2": "חגיגה ג:,  א",
    "path_2": "חגיגה.txt",
    "Conection Type": ""
  },
  {
    "line_index_1": 61,
    "line_index_2": 42,
    "heRef_2": "חגיגה ג:,  ב",
    "path_2": "חגיגה.txt",
    "Conection Type": ""
  },
  {
    "line_index_1": 61,
    "line_index_2": 43,
    "heRef_2": "חגיגה ג:,  ג",
    "path_2": "חגיגה.txt",
    "Conection Type": ""
  },
  {
    "line_index_1": 61,
    "line_index_2": 44,
    "heRef_2": "חגיגה ג:,  ד",
    "path_2": "חגיגה.txt",
    "Conection Type": ""
  },
  {
    "line_index_1": 61,
    "line_index_2": 45,
    "heRef_2": "חגיגה ג:,  ה",
    "path_2": "חגיגה.txt",
    "Conection Type": ""
  },
  {
    "line_index_1": 61,
    "line_index_2": 46,
    "heRef_2": "חגיגה ג:,  ו",
    "path_2": "חגיגה.txt",
    "Conection Type": ""
  },
  {
    "line_index_1": 61,
    "line_index_2": 47,
    "heRef_2": "חגיגה ג:,  ז",
    "path_2": "חגיגה.txt",
    "Conection Type": ""
  },
  {
    "line_index_1": 61,
    "line_index_2": 48,
    "heRef_2": "חגיגה ג:,  ח",
    "path_2": "חגיגה.txt",
    "Conection Type": ""
  },
  {
    "line_index_1": 61,
    "line_index_2": 49,
    "heRef_2": "חגיגה ג:,  ט",
    "path_2": "חגיגה.txt",
    "Conection Type": ""
  },
  {
    "line_index_1": 61,
    "line_index_2": 50,
    "heRef_2": "חגיגה ג:,  י",
    "path_2": "חגיגה.txt",
    "Conection Type": ""
  },
  {
    "line_index_1": 61,
    "line_index_2": 51,
    "heRef_2": "חגיגה ג:,  יא",
    "path_2": "חגיגה.txt",
    "Conection Type": ""
  },
  {
    "line_index_1": 61,
    "line_index_2": 52,
    "heRef_2": "חגיגה ג:,  יב",
    "path_2": "חגיגה.txt",
    "Conection Type": ""
  },
  {
    "line_index_1": 61,
    "line_index_2": 53,
    "heRef_2": "חגיגה ג:,  יג",
    "path_2": "חגיגה.txt",
    "Conection Type": ""
  },
  {
    "line_index_1": 61,
    "line_index_2": 54,
    "heRef_2": "חגיגה ג:,  יד",
    "path_2": "חגיגה.txt",
    "Conection Type": ""
  },
  {
    "line_index_1": 61,
    "line_index_2": 56,
    "heRef_2": "חגיגה ד.,  א",
    "path_2": "חגיגה.txt",
    "Conection Type": ""
  },
  {
    "line_index_1": 61,
    "line_index_2": 57,
    "heRef_2": "חגיגה ד.,  ב",
    "path_2": "חגיגה.txt",
    "Conection Type": ""
  },
  {
    "line_index_1": 61,
    "line_index_2": 58,
    "heRef_2": "חגיגה ד.,  ג",
    "path_2": "חגיגה.txt",
    "Conection Type": ""
  },
  {
    "line_index_1": 61,
    "line_index_2": 59,
    "heRef_2": "חגיגה ד.,  ד",
    "path_2": "חגיגה.txt",
    "Conection Type": ""
  },
  {
    "line_index_1": 61,
    "line_index_2": 60,
    "heRef_2": "חגיגה ד.,  ה",
    "path_2": "חגיגה.txt",
    "Conection Type": ""
  },
  {
    "line_index_1": 61,
    "line_index_2": 61,
    "heRef_2": "חגיגה ד.,  ו",
    "path_2": "חגיגה.txt",
    "Conection Type": ""
  },
  {
    "line_index_1": 61,
    "line_index_2": 62,
    "heRef_2": "חגיגה ד.,  ז",
    "path_2": "חגיגה.txt",
    "Conection Type": ""
  },
  {
    "line_index_1": 61,
    "line_index_2": 63,
    "heRef_2": "חגיגה ד.,  ח",
    "path_2": "חגיגה.txt",
    "Conection Type": ""
  },
  {
    "line_index_1": 61,
    "line_index_2": 64,
    "heRef_2": "חגיגה ד.,  ט",
    "path_2": "חגיגה.txt",
    "Conection Type": ""
  },
  {
    "line_index_1": 61,
    "line_index_2": 65,
    "heRef_2": "חגיגה ד.,  י",
    "path_2": "חגיגה.txt",
    "Conection Type": ""
  },
  {
    "line_index_1": 61,
    "line_index_2": 66,
    "heRef_2": "חגיגה ד.,  יא",
    "path_2": "חגיגה.txt",
    "Conection Type": ""
  },
  {
    "line_index_1": 61,
    "line_index_2": 67,
    "heRef_2": "חגיגה ד.,  יב",
    "path_2": "חגיגה.txt",
    "Conection Type": ""
  },
  {
    "line_index_1": 61,
    "line_index_2": 68,
    "heRef_2": "חגיגה ד.,  יג",
    "path_2": "חגיגה.txt",
    "Conection Type": ""
  },
  {
    "line_index_1": 61,
    "line_index_2": 232,
    "heRef_2": "קהלת יב, יא",
    "path_2": "קהלת.txt",
    "Conection Type": ""
  },
  {
    "line_index_1": 61,
    "line_index_2": 635,
    "heRef_2": "שמות כג, ב",
    "path_2": "שמות.txt",
    "Conection Type": ""
  },
  {
    "line_index_1": 61,
    "line_index_2": 4091,
    "heRef_2": "סנהדרין קה:,  א",
    "path_2": "סנהדרין.txt",
    "Conection Type": ""
  },
  {
    "line_index_1": 107,
    "line_index_2": 40,
    "heRef_2": "משלי ב, ד",
    "path_2": "משלי.txt",
    "Conection Type": ""
  },
  {
    "line_index_1": 129,
    "line_index_2": 209,
    "heRef_2": "חידושי אגדות על נדרים פא., ד",
    "path_2": "חידושי אגדות על נדרים.txt",
    "Conection Type": ""
  },
  {
    "line_index_1": 182,
    "line_index_2": 3529,
    "heRef_2": "בבא מציעא קז., יב",
    "path_2": "בבא מציעא.txt",
    "Conection Type": "commentary"
  },
  {
    "line_index_1": 183,
    "line_index_2": 3532,
    "heRef_2": "בבא מציעא קז., טו",
    "path_2": "בבא מציעא.txt",
    "Conection Type": "commentary"
  },
  {
    "line_index_1": 189,
    "line_index_2": 3548,
    "heRef_2": "בבא מציעא קז:, טו",
    "path_2": "בבא מציעא.txt",
    "Conection Type": "commentary"
  },
  {
    "line_index_1": 186,
    "line_index_2": 3537,
    "heRef_2": "בבא מציעא קז:, ד",
    "path_2": "בבא מציעא.txt",
    "Conection Type": "commentary"
  },
  {
    "line_index_1": 188,
    "line_index_2": 3539,
    "heRef_2": "בבא מציעא קז:, ו",
    "path_2": "בבא מציעא.txt",
    "Conection Type": "commentary"
  },
  {
    "line_index_1": 191,
    "line_index_2": 3753,
    "heRef_2": "בבא מציעא קיד:, ג",
    "path_2": "בבא מציעא.txt",
    "Conection Type": "commentary"
  },
  {
    "line_index_1": 192,
    "line_index_2": 3754,
    "heRef_2": "בבא מציעא קיד:, ד",
    "path_2": "בבא מציעא.txt",
    "Conection Type": "commentary"
  },
  {
    "line_index_1": 4,
    "line_index_2": 672,
    "heRef_2": "בבא מציעא כ:, ג",
    "path_2": "בבא מציעא.txt",
    "Conection Type": "commentary"
  },
  {
    "line_index_1": 6,
    "line_index_2": 791,
    "heRef_2": "בבא מציעא כג:, יא",
    "path_2": "בבא מציעא.txt",
    "Conection Type": "commentary"
  },
  {
    "line_index_1": 12,
    "line_index_2": 1013,
    "heRef_2": "בבא מציעא כט:, כד",
    "path_2": "בבא מציעא.txt",
    "Conection Type": "commentary"
  },
  {
    "line_index_1": 14,
    "line_index_2": 1043,
    "heRef_2": "בבא מציעא ל:, יא",
    "path_2": "בבא מציעא.txt",
    "Conection Type": "commentary"
  },
  {
    "line_index_1": 20,
    "line_index_2": 1089,
    "heRef_2": "בבא מציעא לא:, יא",
    "path_2": "בבא מציעא.txt",
    "Conection Type": "commentary"
  },
  {
    "line_index_1": 18,
    "line_index_2": 1085,
    "heRef_2": "בבא מציעא לא:, ז",
    "path_2": "בבא מציעא.txt",
    "Conection Type": "commentary"
  },
  {
    "line_index_1": 19,
    "line_index_2": 1086,
    "heRef_2": "בבא מציעא לא:, ח",
    "path_2": "בבא מציעא.txt",
    "Conection Type": "commentary"
  },
  {
    "line_index_1": 22,
    "line_index_2": 1148,
    "heRef_2": "בבא מציעא לג., יא",
    "path_2": "בבא מציעא.txt",
    "Conection Type": "commentary"
  },
  {
    "line_index_1": 23,
    "line_index_2": 1151,
    "heRef_2": "בבא מציעא לג., יד",
    "path_2": "בבא מציעא.txt",
    "Conection Type": "commentary"
  },
  {
    "line_index_1": 24,
    "line_index_2": 1152,
    "heRef_2": "בבא מציעא לג., טו",
    "path_2": "בבא מציעא.txt",
    "Conection Type": "commentary"
  },
  {
    "line_index_1": 25,
    "line_index_2": 1155,
    "heRef_2": "בבא מציעא לג., יח",
    "path_2": "בבא מציעא.txt",
    "Conection Type": "commentary"
  },
  {
    "line_index_1": 27,
    "line_index_2": 1160,
    "heRef_2": "בבא מציעא לג:, ג",
    "path_2": "בבא מציעא.txt",
    "Conection Type": "commentary"
  },
  {
    "line_index_1": 39,
    "line_index_2": 1632,
    "heRef_2": "בבא מציעא מט., ו",
    "path_2": "בבא מציעא.txt",
    "Conection Type": "commentary"
  },
  {
    "line_index_1": 40,
    "line_index_2": 1633,
    "heRef_2": "בבא מציעא מט., ז",
    "path_2": "בבא מציעא.txt",
    "Conection Type": "commentary"
  },
  {
    "line_index_1": 45,
    "line_index_2": 1912,
    "heRef_2": "בבא מציעא נח:, יא",
    "path_2": "בבא מציעא.txt",
    "Conection Type": "commentary"
  },
  {
    "line_index_1": 46,
    "line_index_2": 1913,
    "heRef_2": "בבא מציעא נח:, יב",
    "path_2": "בבא מציעא.txt",
    "Conection Type": "commentary"
  },
  {
    "line_index_1": 47,
    "line_index_2": 1913,
    "heRef_2": "בבא מציעא נח:, יב",
    "path_2": "בבא מציעא.txt",
    "Conection Type": "commentary"
  },
  {
    "line_index_1": 42,
    "line_index_2": 1909,
    "heRef_2": "בבא מציעא נח:, ח",
    "path_2": "בבא מציעא.txt",
    "Conection Type": "commentary"
  },
  {
    "line_index_1": 43,
    "line_index_2": 1909,
    "heRef_2": "בבא מציעא נח:, ח",
    "path_2": "בבא מציעא.txt",
    "Conection Type": "commentary"
  },
  {
    "line_index_1": 50,
    "line_index_2": 1917,
    "heRef_2": "בבא מציעא נט., א",
    "path_2": "בבא מציעא.txt",
    "Conection Type": "commentary"
  },
  {
    "line_index_1": 59,
    "line_index_2": 1927,
    "heRef_2": "בבא מציעא נט., יא",
    "path_2": "בבא מציעא.txt",
    "Conection Type": "commentary"
  },
  {
    "line_index_1": 55,
    "line_index_2": 1923,
    "heRef_2": "בבא מציעא נט., ז",
    "path_2": "בבא מציעא.txt",
    "Conection Type": "commentary"
  },
  {
    "line_index_1": 56,
    "line_index_2": 1924,
    "heRef_2": "בבא מציעא נט., ח",
    "path_2": "בבא מציעא.txt",
    "Conection Type": "commentary"
  },
  {
    "line_index_1": 57,
    "line_index_2": 1925,
    "heRef_2": "בבא מציעא נט., ט",
    "path_2": "בבא מציעא.txt",
    "Conection Type": "commentary"
  },
  {
    "line_index_1": 63,
    "line_index_2": 1939,
    "heRef_2": "בבא מציעא נט:, י",
    "path_2": "בבא מציעא.txt",
    "Conection Type": "commentary"
  },
  {
    "line_index_1": 61,
    "line_index_2": 1931,
    "heRef_2": "בבא מציעא נט:, ב",
    "path_2": "בבא מציעא.txt",
    "Conection Type": "commentary"
  },
  {
    "line_index_1": 62,
    "line_index_2": 1935,
    "heRef_2": "בבא מציעא נט:, ו",
    "path_2": "בבא מציעא.txt",
    "Conection Type": "commentary"
  },
  {
    "line_index_1": 65,
    "line_index_2": 1969,
    "heRef_2": "בבא מציעא ס:, ו",
    "path_2": "בבא מציעא.txt",
    "Conection Type": "commentary"
  },
  {
    "line_index_1": 68,
    "line_index_2": 2006,
    "heRef_2": "בבא מציעא סא:, ד",
    "path_2": "בבא מציעא.txt",
    "Conection Type": "commentary"
  },
  {
    "line_index_1": 73,
    "line_index_2": 2275,
    "heRef_2": "בבא מציעא ע:, ט",
    "path_2": "בבא מציעא.txt",
    "Conection Type": "commentary"
  },
  {
    "line_index_1": 81,
    "line_index_2": 2430,
    "heRef_2": "בבא מציעא עה:, יג",
    "path_2": "בבא מציעא.txt",
    "Conection Type": "commentary"
  },
  {
    "line_index_1": 82,
    "line_index_2": 2430,
    "heRef_2": "בבא מציעא עה:, יג",
    "path_2": "בבא מציעא.txt",
    "Conection Type": "commentary"
  },
  {
    "line_index_1": 79,
    "line_index_2": 2422,
    "heRef_2": "בבא מציעא עה:, ה",
    "path_2": "בבא מציעא.txt",
    "Conection Type": "commentary"
  },
  {
    "line_index_1": 78,
    "line_index_2": 2424,
    "heRef_2": "בבא מציעא עה:, ז",
    "path_2": "בבא מציעא.txt",
    "Conection Type": "commentary"
  },
  {
    "line_index_1": 95,
    "line_index_2": 2661,
    "heRef_2": "בבא מציעא פג:, י",
    "path_2": "בבא מציעא.txt",
    "Conection Type": "commentary"
  },
  {
    "line_index_1": 96,
    "line_index_2": 2662,
    "heRef_2": "בבא מציעא פג:, יא",
    "path_2": "בבא מציעא.txt",
    "Conection Type": "commentary"
  },
  {
    "line_index_1": 97,
    "line_index_2": 2664,
    "heRef_2": "בבא מציעא פג:, יג",
    "path_2": "בבא מציעא.txt",
    "Conection Type": "commentary"
  },
  {
    "line_index_1": 90,
    "line_index_2": 2654,
    "heRef_2": "בבא מציעא פג:, ג",
    "path_2": "בבא מציעא.txt",
    "Conection Type": "commentary"
  },
  {
    "line_index_1": 91,
    "line_index_2": 2655,
    "heRef_2": "בבא מציעא פג:, ד",
    "path_2": "בבא מציעא.txt",
    "Conection Type": "commentary"
  },
  {
    "line_index_1": 92,
    "line_index_2": 2656,
    "heRef_2": "בבא מציעא פג:, ה",
    "path_2": "בבא מציעא.txt",
    "Conection Type": "commentary"
  },
  {
    "line_index_1": 93,
    "line_index_2": 2659,
    "heRef_2": "בבא מציעא פג:, ח",
    "path_2": "בבא מציעא.txt",
    "Conection Type": "commentary"
  },
  {
    "line_index_1": 104,
    "line_index_2": 2676,
    "heRef_2": "בבא מציעא פד., י",
    "path_2": "בבא מציעא.txt",
    "Conection Type": "commentary"
  },
  {
    "line_index_1": 106,
    "line_index_2": 2680,
    "heRef_2": "בבא מציעא פד., יד",
    "path_2": "בבא מציעא.txt",
    "Conection Type": "commentary"
  },
  {
    "line_index_1": 107,
    "line_index_2": 2684,
    "heRef_2": "בבא מציעא פד., יח",
    "path_2": "בבא מציעא.txt",
    "Conection Type": "commentary"
  },
  {
    "line_index_1": 99,
    "line_index_2": 2668,
    "heRef_2": "בבא מציעא פד., ב",
    "path_2": "בבא מציעא.txt",
    "Conection Type": "commentary"
  },
  {
    "line_index_1": 100,
    "line_index_2": 2674,
    "heRef_2": "בבא מציעא פד., ח",
    "path_2": "בבא מציעא.txt",
    "Conection Type": "commentary"
  },
  {
    "line_index_1": 101,
    "line_index_2": 2674,
    "heRef_2": "בבא מציעא פד., ח",
    "path_2": "בבא מציעא.txt",
    "Conection Type": "commentary"
  },
  {
    "line_index_1": 102,
    "line_index_2": 2675,
    "heRef_2": "בבא מציעא פד., ט",
    "path_2": "בבא מציעא.txt",
    "Conection Type": "commentary"
  },
  {
    "line_index_1": 109,
    "line_index_2": 2686,
    "heRef_2": "בבא מציעא פד:, א",
    "path_2": "בבא מציעא.txt",
    "Conection Type": "commentary"
  },
  {
    "line_index_1": 114,
    "line_index_2": 2695,
    "heRef_2": "בבא מציעא פד:, י",
    "path_2": "בבא מציעא.txt",
    "Conection Type": "commentary"
  },
  {
    "line_index_1": 115,
    "line_index_2": 2697,
    "heRef_2": "בבא מציעא פד:, יב",
    "path_2": "בבא מציעא.txt",
    "Conection Type": "commentary"
  },
  {
    "line_index_1": 116,
    "line_index_2": 2701,
    "heRef_2": "בבא מציעא פד:, טז",
    "path_2": "בבא מציעא.txt",
    "Conection Type": "commentary"
  },
  {
    "line_index_1": 117,
    "line_index_2": 2702,
    "heRef_2": "בבא מציעא פד:, יז",
    "path_2": "בבא מציעא.txt",
    "Conection Type": "commentary"
  },
  {
    "line_index_1": 110,
    "line_index_2": 2688,
    "heRef_2": "בבא מציעא פד:, ג",
    "path_2": "בבא מציעא.txt",
    "Conection Type": "commentary"
  },
  {
    "line_index_1": 111,
    "line_index_2": 2689,
    "heRef_2": "בבא מציעא פד:, ד",
    "path_2": "בבא מציעא.txt",
    "Conection Type": "commentary"
  },
  {
    "line_index_1": 112,
    "line_index_2": 2691,
    "heRef_2": "בבא מציעא פד:, ו",
    "path_2": "בבא מציעא.txt",
    "Conection Type": "commentary"
  },
  {
    "line_index_1": 121,
    "line_index_2": 2716,
    "heRef_2": "בבא מציעא פה., יא",
    "path_2": "בבא מציעא.txt",
    "Conection Type": "commentary"
  },
  {
    "line_index_1": 122,
    "line_index_2": 2721,
    "heRef_2": "בבא מציעא פה., טז",
    "path_2": "בבא מציעא.txt",
    "Conection Type": "commentary"
  },
  {
    "line_index_1": 123,
    "line_index_2": 2723,
    "heRef_2": "בבא מציעא פה., יח",
    "path_2": "בבא מציעא.txt",
    "Conection Type": "commentary"
  },
  {
    "line_index_1": 119,
    "line_index_2": 2707,
    "heRef_2": "בבא מציעא פה., ב",
    "path_2": "בבא מציעא.txt",
    "Conection Type": "commentary"
  },
  {
    "line_index_1": 124,
    "line_index_2": 2725,
    "heRef_2": "בבא מציעא פה., כ",
    "path_2": "בבא מציעא.txt",
    "Conection Type": "commentary"
  },
  {
    "line_index_1": 126,
    "line_index_2": 2727,
    "heRef_2": "בבא מציעא פה., כב",
    "path_2": "בבא מציעא.txt",
    "Conection Type": "commentary"
  },
  {
    "line_index_1": 127,
    "line_index_2": 2727,
    "heRef_2": "בבא מציעא פה.,  כב",
    "path_2": "בבא מציעא.txt",
    "Conection Type": "commentary"
  },
  {
    "line_index_1": 127,
    "line_index_2": 2728,
    "heRef_2": "בבא מציעא פה.,  כג",
    "path_2": "בבא מציעא.txt",
    "Conection Type": "commentary"
  },
  {
    "line_index_1": 120,
    "line_index_2": 2711,
    "heRef_2": "בבא מציעא פה.,  ו",
    "path_2": "בבא מציעא.txt",
    "Conection Type": "commentary"
  },
  {
    "line_index_1": 120,
    "line_index_2": 2712,
    "heRef_2": "בבא מציעא פה.,  ז",
    "path_2": "בבא מציעא.txt",
    "Conection Type": "commentary"
  },
  {
    "line_index_1": 129,
    "line_index_2": 2730,
    "heRef_2": "בבא מציעא פה:, א",
    "path_2": "בבא מציעא.txt",
    "Conection Type": "commentary"
  },
  {
    "line_index_1": 134,
    "line_index_2": 2739,
    "heRef_2": "בבא מציעא פה:, י",
    "path_2": "בבא מציעא.txt",
    "Conection Type": "commentary"
  },
  {
    "line_index_1": 135,
    "line_index_2": 2740,
    "heRef_2": "בבא מציעא פה:, יא",
    "path_2": "בבא מציעא.txt",
    "Conection Type": "commentary"
  },
  {
    "line_index_1": 136,
    "line_index_2": 2740,
    "heRef_2": "בבא מציעא פה:, יא",
    "path_2": "בבא מציעא.txt",
    "Conection Type": "commentary"
  },
  {
    "line_index_1": 139,
    "line_index_2": 2740,
    "heRef_2": "בבא מציעא פה:, יא",
    "path_2": "בבא מציעא.txt",
    "Conection Type": "commentary"
  },
  {
    "line_index_1": 137,
    "line_index_2": 2741,
    "heRef_2": "בבא מציעא פה:, יב",
    "path_2": "בבא מציעא.txt",
    "Conection Type": "commentary"
  },
  {
    "line_index_1": 130,
    "line_index_2": 2732,
    "heRef_2": "בבא מציעא פה:, ג",
    "path_2": "בבא מציעא.txt",
    "Conection Type": "commentary"
  },
  {
    "line_index_1": 131,
    "line_index_2": 2734,
    "heRef_2": "בבא מציעא פה:, ה",
    "path_2": "בבא מציעא.txt",
    "Conection Type": "commentary"
  },
  {
    "line_index_1": 132,
    "line_index_2": 2736,
    "heRef_2": "בבא מציעא פה:, ז",
    "path_2": "בבא מציעא.txt",
    "Conection Type": "commentary"
  },
  {
    "line_index_1": 133,
    "line_index_2": 2737,
    "heRef_2": "בבא מציעא פה:, ח",
    "path_2": "בבא מציעא.txt",
    "Conection Type": "commentary"
  },
  {
    "line_index_1": 142,
    "line_index_2": 2746,
    "heRef_2": "בבא מציעא פו., א",
    "path_2": "בבא מציעא.txt",
    "Conection Type": "commentary"
  },
  {
    "line_index_1": 146,
    "line_index_2": 2756,
    "heRef_2": "בבא מציעא פו., יא",
    "path_2": "בבא מציעא.txt",
    "Conection Type": "commentary"
  },
  {
    "line_index_1": 143,
    "line_index_2": 2750,
    "heRef_2": "בבא מציעא פו., ה",
    "path_2": "בבא מציעא.txt",
    "Conection Type": "commentary"
  },
  {
    "line_index_1": 144,
    "line_index_2": 2752,
    "heRef_2": "בבא מציעא פו., ז",
    "path_2": "בבא מציעא.txt",
    "Conection Type": "commentary"
  },
  {
    "line_index_1": 145,
    "line_index_2": 2754,
    "heRef_2": "בבא מציעא פו., ט",
    "path_2": "בבא מציעא.txt",
    "Conection Type": "commentary"
  },
  {
    "line_index_1": 155,
    "line_index_2": 2770,
    "heRef_2": "בבא מציעא פו:, י",
    "path_2": "בבא מציעא.txt",
    "Conection Type": "commentary"
  },
  {
    "line_index_1": 156,
    "line_index_2": 2770,
    "heRef_2": "בבא מציעא פו:, י",
    "path_2": "בבא מציעא.txt",
    "Conection Type": "commentary"
  },
  {
    "line_index_1": 157,
    "line_index_2": 2771,
    "heRef_2": "בבא מציעא פו:,  יא",
    "path_2": "בבא מציעא.txt",
    "Conection Type": "commentary"
  },
  {
    "line_index_1": 157,
    "line_index_2": 2772,
    "heRef_2": "בבא מציעא פו:,  יב",
    "path_2": "בבא מציעא.txt",
    "Conection Type": "commentary"
  },
  {
    "line_index_1": 158,
    "line_index_2": 2775,
    "heRef_2": "בבא מציעא פו:, טו",
    "path_2": "בבא מציעא.txt",
    "Conection Type": "commentary"
  },
  {
    "line_index_1": 159,
    "line_index_2": 2776,
    "heRef_2": "בבא מציעא פו:, טז",
    "path_2": "בבא מציעא.txt",
    "Conection Type": "commentary"
  },
  {
    "line_index_1": 160,
    "line_index_2": 2777,
    "heRef_2": "בבא מציעא פו:, יז",
    "path_2": "בבא מציעא.txt",
    "Conection Type": "commentary"
  },
  {
    "line_index_1": 148,
    "line_index_2": 2762,
    "heRef_2": "בבא מציעא פו:, ב",
    "path_2": "בבא מציעא.txt",
    "Conection Type": "commentary"
  },
  {
    "line_index_1": 149,
    "line_index_2": 2763,
    "heRef_2": "בבא מציעא פו:, ג",
    "path_2": "בבא מציעא.txt",
    "Conection Type": "commentary"
  },
  {
    "line_index_1": 150,
    "line_index_2": 2764,
    "heRef_2": "בבא מציעא פו:, ד",
    "path_2": "בבא מציעא.txt",
    "Conection Type": "commentary"
  },
  {
    "line_index_1": 151,
    "line_index_2": 2765,
    "heRef_2": "בבא מציעא פו:, ה",
    "path_2": "בבא מציעא.txt",
    "Conection Type": "commentary"
  },
  {
    "line_index_1": 152,
    "line_index_2": 2765,
    "heRef_2": "בבא מציעא פו:, ה",
    "path_2": "בבא מציעא.txt",
    "Conection Type": "commentary"
  },
  {
    "line_index_1": 153,
    "line_index_2": 2768,
    "heRef_2": "בבא מציעא פו:, ח",
    "path_2": "בבא מציעא.txt",
    "Conection Type": "commentary"
  },
  {
    "line_index_1": 154,
    "line_index_2": 2769,
    "heRef_2": "בבא מציעא פו:, ט",
    "path_2": "בבא מציעא.txt",
    "Conection Type": "commentary"
  },
  {
    "line_index_1": 167,
    "line_index_2": 2783,
    "heRef_2": "בבא מציעא פז., א",
    "path_2": "בבא מציעא.txt",
    "Conection Type": "commentary"
  },
  {
    "line_index_1": 175,
    "line_index_2": 2792,
    "heRef_2": "בבא מציעא פז., י",
    "path_2": "בבא מציעא.txt",
    "Conection Type": "commentary"
  },
  {
    "line_index_1": 176,
    "line_index_2": 2794,
    "heRef_2": "בבא מציעא פז., יב",
    "path_2": "בבא מציעא.txt",
    "Conection Type": "commentary"
  },
  {
    "line_index_1": 177,
    "line_index_2": 2796,
    "heRef_2": "בבא מציעא פז., יד",
    "path_2": "בבא מציעא.txt",
    "Conection Type": "commentary"
  },
  {
    "line_index_1": 178,
    "line_index_2": 2797,
    "heRef_2": "בבא מציעא פז., טו",
    "path_2": "בבא מציעא.txt",
    "Conection Type": "commentary"
  },
  {
    "line_index_1": 168,
    "line_index_2": 2784,
    "heRef_2": "בבא מציעא פז., ב",
    "path_2": "בבא מציעא.txt",
    "Conection Type": "commentary"
  },
  {
    "line_index_1": 169,
    "line_index_2": 2785,
    "heRef_2": "בבא מציעא פז., ג",
    "path_2": "בבא מציעא.txt",
    "Conection Type": "commentary"
  },
  {
    "line_index_1": 170,
    "line_index_2": 2786,
    "heRef_2": "בבא מציעא פז., ד",
    "path_2": "בבא מציעא.txt",
    "Conection Type": "commentary"
  },
  {
    "line_index_1": 171,
    "line_index_2": 2788,
    "heRef_2": "בבא מציעא פז., ו",
    "path_2": "בבא מציעא.txt",
    "Conection Type": "commentary"
  },
  {
    "line_index_1": 172,
    "line_index_2": 2789,
    "heRef_2": "בבא מציעא פז., ז",
    "path_2": "בבא מציעא.txt",
    "Conection Type": "commentary"
  },
  {
    "line_index_1": 173,
    "line_index_2": 2790,
    "heRef_2": "בבא מציעא פז., ח",
    "path_2": "בבא מציעא.txt",
    "Conection Type": "commentary"
  },
  {
    "line_index_1": 174,
    "line_index_2": 2791,
    "heRef_2": "בבא מציעא פז., ט",
    "path_2": "בבא מציעא.txt",
    "Conection Type": "commentary"
  }
]