[
  {
    "line_index_1": 241,
    "line_index_2": 1044,
    "heRef_2": "גיטין לו.,  א",
    "path_2": "גיטין.txt",
    "Conection Type": ""
  },
  {
    "line_index_1": 102,
    "line_index_2": 2161,
    "heRef_2": "גיטין סו:,  א",
    "path_2": "גיטין.txt",
    "Conection Type": ""
  },
  {
    "line_index_1": 241,
    "line_index_2": 2454,
    "heRef_2": "גיטין עד.,  א",
    "path_2": "גיטין.txt",
    "Conection Type": ""
  },
  {
    "line_index_1": 112,
    "line_index_2": 2705,
    "heRef_2": "כתובות צח.,  א",
    "path_2": "כתובות.txt",
    "Conection Type": ""
  },
  {
    "line_index_1": 5,
    "line_index_2": 3,
    "heRef_2": "משנה ערכין א, א",
    "path_2": "משנה ערכין.txt",
    "Conection Type": "commentary"
  },
  {
    "line_index_1": 6,
    "line_index_2": 3,
    "heRef_2": "משנה ערכין א, א",
    "path_2": "משנה ערכין.txt",
    "Conection Type": "commentary"
  },
  {
    "line_index_1": 7,
    "line_index_2": 3,
    "heRef_2": "משנה ערכין א, א",
    "path_2": "משנה ערכין.txt",
    "Conection Type": "commentary"
  },
  {
    "line_index_1": 9,
    "line_index_2": 4,
    "heRef_2": "משנה ערכין א, ב",
    "path_2": "משנה ערכין.txt",
    "Conection Type": "commentary"
  },
  {
    "line_index_1": 10,
    "line_index_2": 4,
    "heRef_2": "משנה ערכין א, ב",
    "path_2": "משנה ערכין.txt",
    "Conection Type": "commentary"
  },
  {
    "line_index_1": 12,
    "line_index_2": 5,
    "heRef_2": "משנה ערכין א, ג",
    "path_2": "משנה ערכין.txt",
    "Conection Type": "commentary"
  },
  {
    "line_index_1": 14,
    "line_index_2": 6,
    "heRef_2": "משנה ערכין א, ד",
    "path_2": "משנה ערכין.txt",
    "Conection Type": "commentary"
  },
  {
    "line_index_1": 14,
    "line_index_2": 3139,
    "heRef_2": "סנהדרין פ.,  א",
    "path_2": "סנהדרין.txt",
    "Conection Type": ""
  },
  {
    "line_index_1": 17,
    "line_index_2": 8,
    "heRef_2": "משנה ערכין ב, א",
    "path_2": "משנה ערכין.txt",
    "Conection Type": "commentary"
  },
  {
    "line_index_1": 18,
    "line_index_2": 8,
    "heRef_2": "משנה ערכין ב, א",
    "path_2": "משנה ערכין.txt",
    "Conection Type": "commentary"
  },
  {
    "line_index_1": 19,
    "line_index_2": 8,
    "heRef_2": "משנה ערכין ב, א",
    "path_2": "משנה ערכין.txt",
    "Conection Type": "commentary"
  },
  {
    "line_index_1": 20,
    "line_index_2": 8,
    "heRef_2": "משנה ערכין ב, א",
    "path_2": "משנה ערכין.txt",
    "Conection Type": "commentary"
  },
  {
    "line_index_1": 22,
    "line_index_2": 9,
    "heRef_2": "משנה ערכין ב, ב",
    "path_2": "משנה ערכין.txt",
    "Conection Type": "commentary"
  },
  {
    "line_index_1": 24,
    "line_index_2": 10,
    "heRef_2": "משנה ערכין ב, ג",
    "path_2": "משנה ערכין.txt",
    "Conection Type": "commentary"
  },
  {
    "line_index_1": 25,
    "line_index_2": 10,
    "heRef_2": "משנה ערכין ב, ג",
    "path_2": "משנה ערכין.txt",
    "Conection Type": "commentary"
  },
  {
    "line_index_1": 26,
    "line_index_2": 10,
    "heRef_2": "משנה ערכין ב, ג",
    "path_2": "משנה ערכין.txt",
    "Conection Type": "commentary"
  },
  {
    "line_index_1": 27,
    "line_index_2": 10,
    "heRef_2": "משנה ערכין ב, ג",
    "path_2": "משנה ערכין.txt",
    "Conection Type": "commentary"
  },
  {
    "line_index_1": 28,
    "line_index_2": 10,
    "heRef_2": "משנה ערכין ב, ג",
    "path_2": "משנה ערכין.txt",
    "Conection Type": "commentary"
  },
  {
    "line_index_1": 30,
    "line_index_2": 11,
    "heRef_2": "משנה ערכין ב, ד",
    "path_2": "משנה ערכין.txt",
    "Conection Type": "commentary"
  },
  {
    "line_index_1": 30,
    "line_index_2": 1315,
    "heRef_2": "סוכה נא:,  א",
    "path_2": "סוכה.txt",
    "Conection Type": ""
  },
  {
    "line_index_1": 31,
    "line_index_2": 11,
    "heRef_2": "משנה ערכין ב, ד",
    "path_2": "משנה ערכין.txt",
    "Conection Type": "commentary"
  },
  {
    "line_index_1": 32,
    "line_index_2": 11,
    "heRef_2": "משנה ערכין ב, ד",
    "path_2": "משנה ערכין.txt",
    "Conection Type": "commentary"
  },
  {
    "line_index_1": 34,
    "line_index_2": 12,
    "heRef_2": "משנה ערכין ב, ה",
    "path_2": "משנה ערכין.txt",
    "Conection Type": "commentary"
  },
  {
    "line_index_1": 34,
    "line_index_2": 1672,
    "heRef_2": "מנחות מט.,  א",
    "path_2": "מנחות.txt",
    "Conection Type": ""
  },
  {
    "line_index_1": 35,
    "line_index_2": 12,
    "heRef_2": "משנה ערכין ב, ה",
    "path_2": "משנה ערכין.txt",
    "Conection Type": "commentary"
  },
  {
    "line_index_1": 36,
    "line_index_2": 12,
    "heRef_2": "משנה ערכין ב, ה",
    "path_2": "משנה ערכין.txt",
    "Conection Type": "commentary"
  },
  {
    "line_index_1": 37,
    "line_index_2": 12,
    "heRef_2": "משנה ערכין ב, ה",
    "path_2": "משנה ערכין.txt",
    "Conection Type": "commentary"
  },
  {
    "line_index_1": 38,
    "line_index_2": 12,
    "heRef_2": "משנה ערכין ב, ה",
    "path_2": "משנה ערכין.txt",
    "Conection Type": "commentary"
  },
  {
    "line_index_1": 40,
    "line_index_2": 13,
    "heRef_2": "משנה ערכין ב, ו",
    "path_2": "משנה ערכין.txt",
    "Conection Type": "commentary"
  },
  {
    "line_index_1": 41,
    "line_index_2": 13,
    "heRef_2": "משנה ערכין ב, ו",
    "path_2": "משנה ערכין.txt",
    "Conection Type": "commentary"
  },
  {
    "line_index_1": 42,
    "line_index_2": 13,
    "heRef_2": "משנה ערכין ב, ו",
    "path_2": "משנה ערכין.txt",
    "Conection Type": "commentary"
  },
  {
    "line_index_1": 43,
    "line_index_2": 13,
    "heRef_2": "משנה ערכין ב, ו",
    "path_2": "משנה ערכין.txt",
    "Conection Type": "commentary"
  },
  {
    "line_index_1": 44,
    "line_index_2": 13,
    "heRef_2": "משנה ערכין ב, ו",
    "path_2": "משנה ערכין.txt",
    "Conection Type": "commentary"
  },
  {
    "line_index_1": 45,
    "line_index_2": 13,
    "heRef_2": "משנה ערכין ב, ו",
    "path_2": "משנה ערכין.txt",
    "Conection Type": "commentary"
  },
  {
    "line_index_1": 46,
    "line_index_2": 13,
    "heRef_2": "משנה ערכין ב, ו",
    "path_2": "משנה ערכין.txt",
    "Conection Type": "commentary"
  },
  {
    "line_index_1": 47,
    "line_index_2": 13,
    "heRef_2": "משנה ערכין ב, ו",
    "path_2": "משנה ערכין.txt",
    "Conection Type": "commentary"
  },
  {
    "line_index_1": 50,
    "line_index_2": 15,
    "heRef_2": "משנה ערכין ג, א",
    "path_2": "משנה ערכין.txt",
    "Conection Type": "commentary"
  },
  {
    "line_index_1": 52,
    "line_index_2": 16,
    "heRef_2": "משנה ערכין ג, ב",
    "path_2": "משנה ערכין.txt",
    "Conection Type": "commentary"
  },
  {
    "line_index_1": 53,
    "line_index_2": 16,
    "heRef_2": "משנה ערכין ג, ב",
    "path_2": "משנה ערכין.txt",
    "Conection Type": "commentary"
  },
  {
    "line_index_1": 54,
    "line_index_2": 16,
    "heRef_2": "משנה ערכין ג, ב",
    "path_2": "משנה ערכין.txt",
    "Conection Type": "commentary"
  },
  {
    "line_index_1": 56,
    "line_index_2": 18,
    "heRef_2": "משנה ערכין ג, ד",
    "path_2": "משנה ערכין.txt",
    "Conection Type": "commentary"
  },
  {
    "line_index_1": 57,
    "line_index_2": 18,
    "heRef_2": "משנה ערכין ג, ד",
    "path_2": "משנה ערכין.txt",
    "Conection Type": "commentary"
  },
  {
    "line_index_1": 59,
    "line_index_2": 19,
    "heRef_2": "משנה ערכין ג, ה",
    "path_2": "משנה ערכין.txt",
    "Conection Type": "commentary"
  },
  {
    "line_index_1": 60,
    "line_index_2": 19,
    "heRef_2": "משנה ערכין ג, ה",
    "path_2": "משנה ערכין.txt",
    "Conection Type": "commentary"
  },
  {
    "line_index_1": 61,
    "line_index_2": 19,
    "heRef_2": "משנה ערכין ג, ה",
    "path_2": "משנה ערכין.txt",
    "Conection Type": "commentary"
  },
  {
    "line_index_1": 64,
    "line_index_2": 21,
    "heRef_2": "משנה ערכין ד, א",
    "path_2": "משנה ערכין.txt",
    "Conection Type": "commentary"
  },
  {
    "line_index_1": 66,
    "line_index_2": 22,
    "heRef_2": "משנה ערכין ד, ב",
    "path_2": "משנה ערכין.txt",
    "Conection Type": "commentary"
  },
  {
    "line_index_1": 67,
    "line_index_2": 22,
    "heRef_2": "משנה ערכין ד, ב",
    "path_2": "משנה ערכין.txt",
    "Conection Type": "commentary"
  },
  {
    "line_index_1": 67,
    "line_index_2": 830,
    "heRef_2": "פסחים כח.,  א",
    "path_2": "פסחים.txt",
    "Conection Type": ""
  },
  {
    "line_index_1": 68,
    "line_index_2": 22,
    "heRef_2": "משנה ערכין ד, ב",
    "path_2": "משנה ערכין.txt",
    "Conection Type": "commentary"
  },
  {
    "line_index_1": 70,
    "line_index_2": 23,
    "heRef_2": "משנה ערכין ד, ג",
    "path_2": "משנה ערכין.txt",
    "Conection Type": "commentary"
  },
  {
    "line_index_1": 71,
    "line_index_2": 23,
    "heRef_2": "משנה ערכין ד, ג",
    "path_2": "משנה ערכין.txt",
    "Conection Type": "commentary"
  },
  {
    "line_index_1": 73,
    "line_index_2": 24,
    "heRef_2": "משנה ערכין ד, ד",
    "path_2": "משנה ערכין.txt",
    "Conection Type": "commentary"
  },
  {
    "line_index_1": 74,
    "line_index_2": 24,
    "heRef_2": "משנה ערכין ד, ד",
    "path_2": "משנה ערכין.txt",
    "Conection Type": "commentary"
  },
  {
    "line_index_1": 75,
    "line_index_2": 24,
    "heRef_2": "משנה ערכין ד, ד",
    "path_2": "משנה ערכין.txt",
    "Conection Type": "commentary"
  },
  {
    "line_index_1": 76,
    "line_index_2": 24,
    "heRef_2": "משנה ערכין ד, ד",
    "path_2": "משנה ערכין.txt",
    "Conection Type": "commentary"
  },
  {
    "line_index_1": 79,
    "line_index_2": 26,
    "heRef_2": "משנה ערכין ה, א",
    "path_2": "משנה ערכין.txt",
    "Conection Type": "commentary"
  },
  {
    "line_index_1": 80,
    "line_index_2": 26,
    "heRef_2": "משנה ערכין ה, א",
    "path_2": "משנה ערכין.txt",
    "Conection Type": "commentary"
  },
  {
    "line_index_1": 81,
    "line_index_2": 26,
    "heRef_2": "משנה ערכין ה, א",
    "path_2": "משנה ערכין.txt",
    "Conection Type": "commentary"
  },
  {
    "line_index_1": 82,
    "line_index_2": 26,
    "heRef_2": "משנה ערכין ה, א",
    "path_2": "משנה ערכין.txt",
    "Conection Type": "commentary"
  },
  {
    "line_index_1": 83,
    "line_index_2": 26,
    "heRef_2": "משנה ערכין ה, א",
    "path_2": "משנה ערכין.txt",
    "Conection Type": "commentary"
  },
  {
    "line_index_1": 84,
    "line_index_2": 26,
    "heRef_2": "משנה ערכין ה, א",
    "path_2": "משנה ערכין.txt",
    "Conection Type": "commentary"
  },
  {
    "line_index_1": 86,
    "line_index_2": 27,
    "heRef_2": "משנה ערכין ה, ב",
    "path_2": "משנה ערכין.txt",
    "Conection Type": "commentary"
  },
  {
    "line_index_1": 87,
    "line_index_2": 27,
    "heRef_2": "משנה ערכין ה, ב",
    "path_2": "משנה ערכין.txt",
    "Conection Type": "commentary"
  },
  {
    "line_index_1": 88,
    "line_index_2": 27,
    "heRef_2": "משנה ערכין ה, ב",
    "path_2": "משנה ערכין.txt",
    "Conection Type": "commentary"
  },
  {
    "line_index_1": 89,
    "line_index_2": 27,
    "heRef_2": "משנה ערכין ה, ב",
    "path_2": "משנה ערכין.txt",
    "Conection Type": "commentary"
  },
  {
    "line_index_1": 90,
    "line_index_2": 27,
    "heRef_2": "משנה ערכין ה, ב",
    "path_2": "משנה ערכין.txt",
    "Conection Type": "commentary"
  },
  {
    "line_index_1": 91,
    "line_index_2": 27,
    "heRef_2": "משנה ערכין ה, ב",
    "path_2": "משנה ערכין.txt",
    "Conection Type": "commentary"
  },
  {
    "line_index_1": 92,
    "line_index_2": 27,
    "heRef_2": "משנה ערכין ה, ב",
    "path_2": "משנה ערכין.txt",
    "Conection Type": "commentary"
  },
  {
    "line_index_1": 94,
    "line_index_2": 28,
    "heRef_2": "משנה ערכין ה, ג",
    "path_2": "משנה ערכין.txt",
    "Conection Type": "commentary"
  },
  {
    "line_index_1": 95,
    "line_index_2": 28,
    "heRef_2": "משנה ערכין ה, ג",
    "path_2": "משנה ערכין.txt",
    "Conection Type": "commentary"
  },
  {
    "line_index_1": 96,
    "line_index_2": 28,
    "heRef_2": "משנה ערכין ה, ג",
    "path_2": "משנה ערכין.txt",
    "Conection Type": "commentary"
  },
  {
    "line_index_1": 98,
    "line_index_2": 29,
    "heRef_2": "משנה ערכין ה, ד",
    "path_2": "משנה ערכין.txt",
    "Conection Type": "commentary"
  },
  {
    "line_index_1": 99,
    "line_index_2": 29,
    "heRef_2": "משנה ערכין ה, ד",
    "path_2": "משנה ערכין.txt",
    "Conection Type": "commentary"
  },
  {
    "line_index_1": 101,
    "line_index_2": 30,
    "heRef_2": "משנה ערכין ה, ה",
    "path_2": "משנה ערכין.txt",
    "Conection Type": "commentary"
  },
  {
    "line_index_1": 102,
    "line_index_2": 30,
    "heRef_2": "משנה ערכין ה, ה",
    "path_2": "משנה ערכין.txt",
    "Conection Type": "commentary"
  },
  {
    "line_index_1": 103,
    "line_index_2": 30,
    "heRef_2": "משנה ערכין ה, ה",
    "path_2": "משנה ערכין.txt",
    "Conection Type": "commentary"
  },
  {
    "line_index_1": 105,
    "line_index_2": 31,
    "heRef_2": "משנה ערכין ה, ו",
    "path_2": "משנה ערכין.txt",
    "Conection Type": "commentary"
  },
  {
    "line_index_1": 105,
    "line_index_2": 2884,
    "heRef_2": "זבחים פט.,  א",
    "path_2": "זבחים.txt",
    "Conection Type": ""
  },
  {
    "line_index_1": 106,
    "line_index_2": 31,
    "heRef_2": "משנה ערכין ה, ו",
    "path_2": "משנה ערכין.txt",
    "Conection Type": "commentary"
  },
  {
    "line_index_1": 107,
    "line_index_2": 31,
    "heRef_2": "משנה ערכין ה, ו",
    "path_2": "משנה ערכין.txt",
    "Conection Type": "commentary"
  },
  {
    "line_index_1": 108,
    "line_index_2": 31,
    "heRef_2": "משנה ערכין ה, ו",
    "path_2": "משנה ערכין.txt",
    "Conection Type": "commentary"
  },
  {
    "line_index_1": 109,
    "line_index_2": 31,
    "heRef_2": "משנה ערכין ה, ו",
    "path_2": "משנה ערכין.txt",
    "Conection Type": "commentary"
  },
  {
    "line_index_1": 112,
    "line_index_2": 33,
    "heRef_2": "משנה ערכין ו, א",
    "path_2": "משנה ערכין.txt",
    "Conection Type": "commentary"
  },
  {
    "line_index_1": 113,
    "line_index_2": 33,
    "heRef_2": "משנה ערכין ו, א",
    "path_2": "משנה ערכין.txt",
    "Conection Type": "commentary"
  },
  {
    "line_index_1": 115,
    "line_index_2": 34,
    "heRef_2": "משנה ערכין ו, ב",
    "path_2": "משנה ערכין.txt",
    "Conection Type": "commentary"
  },
  {
    "line_index_1": 116,
    "line_index_2": 34,
    "heRef_2": "משנה ערכין ו, ב",
    "path_2": "משנה ערכין.txt",
    "Conection Type": "commentary"
  },
  {
    "line_index_1": 117,
    "line_index_2": 34,
    "heRef_2": "משנה ערכין ו, ב",
    "path_2": "משנה ערכין.txt",
    "Conection Type": "commentary"
  },
  {
    "line_index_1": 118,
    "line_index_2": 34,
    "heRef_2": "משנה ערכין ו, ב",
    "path_2": "משנה ערכין.txt",
    "Conection Type": "commentary"
  },
  {
    "line_index_1": 118,
    "line_index_2": 910,
    "heRef_2": "פסחים לא., א",
    "path_2": "פסחים.txt",
    "Conection Type": ""
  },
  {
    "line_index_1": 120,
    "line_index_2": 35,
    "heRef_2": "משנה ערכין ו, ג",
    "path_2": "משנה ערכין.txt",
    "Conection Type": "commentary"
  },
  {
    "line_index_1": 121,
    "line_index_2": 35,
    "heRef_2": "משנה ערכין ו, ג",
    "path_2": "משנה ערכין.txt",
    "Conection Type": "commentary"
  },
  {
    "line_index_1": 122,
    "line_index_2": 35,
    "heRef_2": "משנה ערכין ו, ג",
    "path_2": "משנה ערכין.txt",
    "Conection Type": "commentary"
  },
  {
    "line_index_1": 123,
    "line_index_2": 35,
    "heRef_2": "משנה ערכין ו, ג",
    "path_2": "משנה ערכין.txt",
    "Conection Type": "commentary"
  },
  {
    "line_index_1": 124,
    "line_index_2": 35,
    "heRef_2": "משנה ערכין ו, ג",
    "path_2": "משנה ערכין.txt",
    "Conection Type": "commentary"
  },
  {
    "line_index_1": 125,
    "line_index_2": 35,
    "heRef_2": "משנה ערכין ו, ג",
    "path_2": "משנה ערכין.txt",
    "Conection Type": "commentary"
  },
  {
    "line_index_1": 126,
    "line_index_2": 35,
    "heRef_2": "משנה ערכין ו, ג",
    "path_2": "משנה ערכין.txt",
    "Conection Type": "commentary"
  },
  {
    "line_index_1": 127,
    "line_index_2": 35,
    "heRef_2": "משנה ערכין ו, ג",
    "path_2": "משנה ערכין.txt",
    "Conection Type": "commentary"
  },
  {
    "line_index_1": 129,
    "line_index_2": 36,
    "heRef_2": "משנה ערכין ו, ד",
    "path_2": "משנה ערכין.txt",
    "Conection Type": "commentary"
  },
  {
    "line_index_1": 130,
    "line_index_2": 36,
    "heRef_2": "משנה ערכין ו, ד",
    "path_2": "משנה ערכין.txt",
    "Conection Type": "commentary"
  },
  {
    "line_index_1": 131,
    "line_index_2": 36,
    "heRef_2": "משנה ערכין ו, ד",
    "path_2": "משנה ערכין.txt",
    "Conection Type": "commentary"
  },
  {
    "line_index_1": 132,
    "line_index_2": 36,
    "heRef_2": "משנה ערכין ו, ד",
    "path_2": "משנה ערכין.txt",
    "Conection Type": "commentary"
  },
  {
    "line_index_1": 134,
    "line_index_2": 37,
    "heRef_2": "משנה ערכין ו, ה",
    "path_2": "משנה ערכין.txt",
    "Conection Type": "commentary"
  },
  {
    "line_index_1": 135,
    "line_index_2": 37,
    "heRef_2": "משנה ערכין ו, ה",
    "path_2": "משנה ערכין.txt",
    "Conection Type": "commentary"
  },
  {
    "line_index_1": 136,
    "line_index_2": 37,
    "heRef_2": "משנה ערכין ו, ה",
    "path_2": "משנה ערכין.txt",
    "Conection Type": "commentary"
  },
  {
    "line_index_1": 137,
    "line_index_2": 37,
    "heRef_2": "משנה ערכין ו, ה",
    "path_2": "משנה ערכין.txt",
    "Conection Type": "commentary"
  },
  {
    "line_index_1": 138,
    "line_index_2": 37,
    "heRef_2": "משנה ערכין ו, ה",
    "path_2": "משנה ערכין.txt",
    "Conection Type": "commentary"
  },
  {
    "line_index_1": 141,
    "line_index_2": 39,
    "heRef_2": "משנה ערכין ז, א",
    "path_2": "משנה ערכין.txt",
    "Conection Type": "commentary"
  },
  {
    "line_index_1": 142,
    "line_index_2": 39,
    "heRef_2": "משנה ערכין ז, א",
    "path_2": "משנה ערכין.txt",
    "Conection Type": "commentary"
  },
  {
    "line_index_1": 143,
    "line_index_2": 39,
    "heRef_2": "משנה ערכין ז, א",
    "path_2": "משנה ערכין.txt",
    "Conection Type": "commentary"
  },
  {
    "line_index_1": 144,
    "line_index_2": 39,
    "heRef_2": "משנה ערכין ז, א",
    "path_2": "משנה ערכין.txt",
    "Conection Type": "commentary"
  },
  {
    "line_index_1": 145,
    "line_index_2": 39,
    "heRef_2": "משנה ערכין ז, א",
    "path_2": "משנה ערכין.txt",
    "Conection Type": "commentary"
  },
  {
    "line_index_1": 146,
    "line_index_2": 39,
    "heRef_2": "משנה ערכין ז, א",
    "path_2": "משנה ערכין.txt",
    "Conection Type": "commentary"
  },
  {
    "line_index_1": 147,
    "line_index_2": 39,
    "heRef_2": "משנה ערכין ז, א",
    "path_2": "משנה ערכין.txt",
    "Conection Type": "commentary"
  },
  {
    "line_index_1": 148,
    "line_index_2": 39,
    "heRef_2": "משנה ערכין ז, א",
    "path_2": "משנה ערכין.txt",
    "Conection Type": "commentary"
  },
  {
    "line_index_1": 149,
    "line_index_2": 39,
    "heRef_2": "משנה ערכין ז, א",
    "path_2": "משנה ערכין.txt",
    "Conection Type": "commentary"
  },
  {
    "line_index_1": 151,
    "line_index_2": 40,
    "heRef_2": "משנה ערכין ז, ב",
    "path_2": "משנה ערכין.txt",
    "Conection Type": "commentary"
  },
  {
    "line_index_1": 153,
    "line_index_2": 41,
    "heRef_2": "משנה ערכין ז, ג",
    "path_2": "משנה ערכין.txt",
    "Conection Type": "commentary"
  },
  {
    "line_index_1": 154,
    "line_index_2": 41,
    "heRef_2": "משנה ערכין ז, ג",
    "path_2": "משנה ערכין.txt",
    "Conection Type": "commentary"
  },
  {
    "line_index_1": 155,
    "line_index_2": 41,
    "heRef_2": "משנה ערכין ז, ג",
    "path_2": "משנה ערכין.txt",
    "Conection Type": "commentary"
  },
  {
    "line_index_1": 156,
    "line_index_2": 41,
    "heRef_2": "משנה ערכין ז, ג",
    "path_2": "משנה ערכין.txt",
    "Conection Type": "commentary"
  },
  {
    "line_index_1": 158,
    "line_index_2": 42,
    "heRef_2": "משנה ערכין ז, ד",
    "path_2": "משנה ערכין.txt",
    "Conection Type": "commentary"
  },
  {
    "line_index_1": 159,
    "line_index_2": 42,
    "heRef_2": "משנה ערכין ז, ד",
    "path_2": "משנה ערכין.txt",
    "Conection Type": "commentary"
  },
  {
    "line_index_1": 160,
    "line_index_2": 42,
    "heRef_2": "משנה ערכין ז, ד",
    "path_2": "משנה ערכין.txt",
    "Conection Type": "commentary"
  },
  {
    "line_index_1": 162,
    "line_index_2": 43,
    "heRef_2": "משנה ערכין ז, ה",
    "path_2": "משנה ערכין.txt",
    "Conection Type": "commentary"
  },
  {
    "line_index_1": 163,
    "line_index_2": 43,
    "heRef_2": "משנה ערכין ז, ה",
    "path_2": "משנה ערכין.txt",
    "Conection Type": "commentary"
  },
  {
    "line_index_1": 164,
    "line_index_2": 43,
    "heRef_2": "משנה ערכין ז, ה",
    "path_2": "משנה ערכין.txt",
    "Conection Type": "commentary"
  },
  {
    "line_index_1": 165,
    "line_index_2": 43,
    "heRef_2": "משנה ערכין ז, ה",
    "path_2": "משנה ערכין.txt",
    "Conection Type": "commentary"
  },
  {
    "line_index_1": 165,
    "line_index_2": 848,
    "heRef_2": "ראש השנה כט.,  א",
    "path_2": "ראש השנה.txt",
    "Conection Type": ""
  },
  {
    "line_index_1": 166,
    "line_index_2": 43,
    "heRef_2": "משנה ערכין ז, ה",
    "path_2": "משנה ערכין.txt",
    "Conection Type": "commentary"
  },
  {
    "line_index_1": 169,
    "line_index_2": 45,
    "heRef_2": "משנה ערכין ח, א",
    "path_2": "משנה ערכין.txt",
    "Conection Type": "commentary"
  },
  {
    "line_index_1": 170,
    "line_index_2": 45,
    "heRef_2": "משנה ערכין ח, א",
    "path_2": "משנה ערכין.txt",
    "Conection Type": "commentary"
  },
  {
    "line_index_1": 171,
    "line_index_2": 45,
    "heRef_2": "משנה ערכין ח, א",
    "path_2": "משנה ערכין.txt",
    "Conection Type": "commentary"
  },
  {
    "line_index_1": 172,
    "line_index_2": 45,
    "heRef_2": "משנה ערכין ח, א",
    "path_2": "משנה ערכין.txt",
    "Conection Type": "commentary"
  },
  {
    "line_index_1": 173,
    "line_index_2": 45,
    "heRef_2": "משנה ערכין ח, א",
    "path_2": "משנה ערכין.txt",
    "Conection Type": "commentary"
  },
  {
    "line_index_1": 174,
    "line_index_2": 45,
    "heRef_2": "משנה ערכין ח, א",
    "path_2": "משנה ערכין.txt",
    "Conection Type": "commentary"
  },
  {
    "line_index_1": 175,
    "line_index_2": 45,
    "heRef_2": "משנה ערכין ח, א",
    "path_2": "משנה ערכין.txt",
    "Conection Type": "commentary"
  },
  {
    "line_index_1": 176,
    "line_index_2": 45,
    "heRef_2": "משנה ערכין ח, א",
    "path_2": "משנה ערכין.txt",
    "Conection Type": "commentary"
  },
  {
    "line_index_1": 178,
    "line_index_2": 46,
    "heRef_2": "משנה ערכין ח, ב",
    "path_2": "משנה ערכין.txt",
    "Conection Type": "commentary"
  },
  {
    "line_index_1": 179,
    "line_index_2": 46,
    "heRef_2": "משנה ערכין ח, ב",
    "path_2": "משנה ערכין.txt",
    "Conection Type": "commentary"
  },
  {
    "line_index_1": 180,
    "line_index_2": 46,
    "heRef_2": "משנה ערכין ח, ב",
    "path_2": "משנה ערכין.txt",
    "Conection Type": "commentary"
  },
  {
    "line_index_1": 181,
    "line_index_2": 46,
    "heRef_2": "משנה ערכין ח, ב",
    "path_2": "משנה ערכין.txt",
    "Conection Type": "commentary"
  },
  {
    "line_index_1": 182,
    "line_index_2": 46,
    "heRef_2": "משנה ערכין ח, ב",
    "path_2": "משנה ערכין.txt",
    "Conection Type": "commentary"
  },
  {
    "line_index_1": 183,
    "line_index_2": 46,
    "heRef_2": "משנה ערכין ח, ב",
    "path_2": "משנה ערכין.txt",
    "Conection Type": "commentary"
  },
  {
    "line_index_1": 185,
    "line_index_2": 47,
    "heRef_2": "משנה ערכין ח, ג",
    "path_2": "משנה ערכין.txt",
    "Conection Type": "commentary"
  },
  {
    "line_index_1": 186,
    "line_index_2": 47,
    "heRef_2": "משנה ערכין ח, ג",
    "path_2": "משנה ערכין.txt",
    "Conection Type": "commentary"
  },
  {
    "line_index_1": 187,
    "line_index_2": 47,
    "heRef_2": "משנה ערכין ח, ג",
    "path_2": "משנה ערכין.txt",
    "Conection Type": "commentary"
  },
  {
    "line_index_1": 188,
    "line_index_2": 47,
    "heRef_2": "משנה ערכין ח, ג",
    "path_2": "משנה ערכין.txt",
    "Conection Type": "commentary"
  },
  {
    "line_index_1": 190,
    "line_index_2": 48,
    "heRef_2": "משנה ערכין ח, ד",
    "path_2": "משנה ערכין.txt",
    "Conection Type": "commentary"
  },
  {
    "line_index_1": 191,
    "line_index_2": 48,
    "heRef_2": "משנה ערכין ח, ד",
    "path_2": "משנה ערכין.txt",
    "Conection Type": "commentary"
  },
  {
    "line_index_1": 192,
    "line_index_2": 48,
    "heRef_2": "משנה ערכין ח, ד",
    "path_2": "משנה ערכין.txt",
    "Conection Type": "commentary"
  },
  {
    "line_index_1": 193,
    "line_index_2": 48,
    "heRef_2": "משנה ערכין ח, ד",
    "path_2": "משנה ערכין.txt",
    "Conection Type": "commentary"
  },
  {
    "line_index_1": 194,
    "line_index_2": 48,
    "heRef_2": "משנה ערכין ח, ד",
    "path_2": "משנה ערכין.txt",
    "Conection Type": "commentary"
  },
  {
    "line_index_1": 196,
    "line_index_2": 49,
    "heRef_2": "משנה ערכין ח, ה",
    "path_2": "משנה ערכין.txt",
    "Conection Type": "commentary"
  },
  {
    "line_index_1": 197,
    "line_index_2": 49,
    "heRef_2": "משנה ערכין ח, ה",
    "path_2": "משנה ערכין.txt",
    "Conection Type": "commentary"
  },
  {
    "line_index_1": 198,
    "line_index_2": 49,
    "heRef_2": "משנה ערכין ח, ה",
    "path_2": "משנה ערכין.txt",
    "Conection Type": "commentary"
  },
  {
    "line_index_1": 199,
    "line_index_2": 49,
    "heRef_2": "משנה ערכין ח, ה",
    "path_2": "משנה ערכין.txt",
    "Conection Type": "commentary"
  },
  {
    "line_index_1": 199,
    "line_index_2": 809,
    "heRef_2": "נדה כג.,  טו",
    "path_2": "נדה.txt",
    "Conection Type": ""
  },
  {
    "line_index_1": 199,
    "line_index_2": 810,
    "heRef_2": "נדה כג.,  טז",
    "path_2": "נדה.txt",
    "Conection Type": ""
  },
  {
    "line_index_1": 201,
    "line_index_2": 50,
    "heRef_2": "משנה ערכין ח, ו",
    "path_2": "משנה ערכין.txt",
    "Conection Type": "commentary"
  },
  {
    "line_index_1": 202,
    "line_index_2": 50,
    "heRef_2": "משנה ערכין ח, ו",
    "path_2": "משנה ערכין.txt",
    "Conection Type": "commentary"
  },
  {
    "line_index_1": 203,
    "line_index_2": 50,
    "heRef_2": "משנה ערכין ח, ו",
    "path_2": "משנה ערכין.txt",
    "Conection Type": "commentary"
  },
  {
    "line_index_1": 203,
    "line_index_2": 3429,
    "heRef_2": "סנהדרין פח., ד",
    "path_2": "סנהדרין.txt",
    "Conection Type": ""
  },
  {
    "line_index_1": 204,
    "line_index_2": 50,
    "heRef_2": "משנה ערכין ח, ו",
    "path_2": "משנה ערכין.txt",
    "Conection Type": "commentary"
  },
  {
    "line_index_1": 205,
    "line_index_2": 50,
    "heRef_2": "משנה ערכין ח, ו",
    "path_2": "משנה ערכין.txt",
    "Conection Type": "commentary"
  },
  {
    "line_index_1": 206,
    "line_index_2": 50,
    "heRef_2": "משנה ערכין ח, ו",
    "path_2": "משנה ערכין.txt",
    "Conection Type": "commentary"
  },
  {
    "line_index_1": 208,
    "line_index_2": 51,
    "heRef_2": "משנה ערכין ח, ז",
    "path_2": "משנה ערכין.txt",
    "Conection Type": "commentary"
  },
  {
    "line_index_1": 209,
    "line_index_2": 51,
    "heRef_2": "משנה ערכין ח, ז",
    "path_2": "משנה ערכין.txt",
    "Conection Type": "commentary"
  },
  {
    "line_index_1": 210,
    "line_index_2": 51,
    "heRef_2": "משנה ערכין ח, ז",
    "path_2": "משנה ערכין.txt",
    "Conection Type": "commentary"
  },
  {
    "line_index_1": 211,
    "line_index_2": 51,
    "heRef_2": "משנה ערכין ח, ז",
    "path_2": "משנה ערכין.txt",
    "Conection Type": "commentary"
  },
  {
    "line_index_1": 212,
    "line_index_2": 51,
    "heRef_2": "משנה ערכין ח, ז",
    "path_2": "משנה ערכין.txt",
    "Conection Type": "commentary"
  },
  {
    "line_index_1": 213,
    "line_index_2": 51,
    "heRef_2": "משנה ערכין ח, ז",
    "path_2": "משנה ערכין.txt",
    "Conection Type": "commentary"
  },
  {
    "line_index_1": 214,
    "line_index_2": 51,
    "heRef_2": "משנה ערכין ח, ז",
    "path_2": "משנה ערכין.txt",
    "Conection Type": "commentary"
  },
  {
    "line_index_1": 215,
    "line_index_2": 51,
    "heRef_2": "משנה ערכין ח, ז",
    "path_2": "משנה ערכין.txt",
    "Conection Type": "commentary"
  },
  {
    "line_index_1": 218,
    "line_index_2": 53,
    "heRef_2": "משנה ערכין ט, א",
    "path_2": "משנה ערכין.txt",
    "Conection Type": "commentary"
  },
  {
    "line_index_1": 219,
    "line_index_2": 53,
    "heRef_2": "משנה ערכין ט, א",
    "path_2": "משנה ערכין.txt",
    "Conection Type": "commentary"
  },
  {
    "line_index_1": 220,
    "line_index_2": 53,
    "heRef_2": "משנה ערכין ט, א",
    "path_2": "משנה ערכין.txt",
    "Conection Type": "commentary"
  },
  {
    "line_index_1": 221,
    "line_index_2": 53,
    "heRef_2": "משנה ערכין ט, א",
    "path_2": "משנה ערכין.txt",
    "Conection Type": "commentary"
  },
  {
    "line_index_1": 222,
    "line_index_2": 53,
    "heRef_2": "משנה ערכין ט, א",
    "path_2": "משנה ערכין.txt",
    "Conection Type": "commentary"
  },
  {
    "line_index_1": 224,
    "line_index_2": 54,
    "heRef_2": "משנה ערכין ט, ב",
    "path_2": "משנה ערכין.txt",
    "Conection Type": "commentary"
  },
  {
    "line_index_1": 225,
    "line_index_2": 54,
    "heRef_2": "משנה ערכין ט, ב",
    "path_2": "משנה ערכין.txt",
    "Conection Type": "commentary"
  },
  {
    "line_index_1": 226,
    "line_index_2": 54,
    "heRef_2": "משנה ערכין ט, ב",
    "path_2": "משנה ערכין.txt",
    "Conection Type": "commentary"
  },
  {
    "line_index_1": 227,
    "line_index_2": 54,
    "heRef_2": "משנה ערכין ט, ב",
    "path_2": "משנה ערכין.txt",
    "Conection Type": "commentary"
  },
  {
    "line_index_1": 228,
    "line_index_2": 54,
    "heRef_2": "משנה ערכין ט, ב",
    "path_2": "משנה ערכין.txt",
    "Conection Type": "commentary"
  },
  {
    "line_index_1": 229,
    "line_index_2": 54,
    "heRef_2": "משנה ערכין ט, ב",
    "path_2": "משנה ערכין.txt",
    "Conection Type": "commentary"
  },
  {
    "line_index_1": 230,
    "line_index_2": 54,
    "heRef_2": "משנה ערכין ט, ב",
    "path_2": "משנה ערכין.txt",
    "Conection Type": "commentary"
  },
  {
    "line_index_1": 232,
    "line_index_2": 55,
    "heRef_2": "משנה ערכין ט, ג",
    "path_2": "משנה ערכין.txt",
    "Conection Type": "commentary"
  },
  {
    "line_index_1": 233,
    "line_index_2": 55,
    "heRef_2": "משנה ערכין ט, ג",
    "path_2": "משנה ערכין.txt",
    "Conection Type": "commentary"
  },
  {
    "line_index_1": 234,
    "line_index_2": 55,
    "heRef_2": "משנה ערכין ט, ג",
    "path_2": "משנה ערכין.txt",
    "Conection Type": "commentary"
  },
  {
    "line_index_1": 235,
    "line_index_2": 55,
    "heRef_2": "משנה ערכין ט, ג",
    "path_2": "משנה ערכין.txt",
    "Conection Type": "commentary"
  },
  {
    "line_index_1": 236,
    "line_index_2": 55,
    "heRef_2": "משנה ערכין ט, ג",
    "path_2": "משנה ערכין.txt",
    "Conection Type": "commentary"
  },
  {
    "line_index_1": 237,
    "line_index_2": 55,
    "heRef_2": "משנה ערכין ט, ג",
    "path_2": "משנה ערכין.txt",
    "Conection Type": "commentary"
  },
  {
    "line_index_1": 239,
    "line_index_2": 56,
    "heRef_2": "משנה ערכין ט, ד",
    "path_2": "משנה ערכין.txt",
    "Conection Type": "commentary"
  },
  {
    "line_index_1": 240,
    "line_index_2": 56,
    "heRef_2": "משנה ערכין ט, ד",
    "path_2": "משנה ערכין.txt",
    "Conection Type": "commentary"
  },
  {
    "line_index_1": 241,
    "line_index_2": 56,
    "heRef_2": "משנה ערכין ט, ד",
    "path_2": "משנה ערכין.txt",
    "Conection Type": "commentary"
  },
  {
    "line_index_1": 242,
    "line_index_2": 56,
    "heRef_2": "משנה ערכין ט, ד",
    "path_2": "משנה ערכין.txt",
    "Conection Type": "commentary"
  },
  {
    "line_index_1": 244,
    "line_index_2": 57,
    "heRef_2": "משנה ערכין ט, ה",
    "path_2": "משנה ערכין.txt",
    "Conection Type": "commentary"
  },
  {
    "line_index_1": 245,
    "line_index_2": 57,
    "heRef_2": "משנה ערכין ט, ה",
    "path_2": "משנה ערכין.txt",
    "Conection Type": "commentary"
  },
  {
    "line_index_1": 247,
    "line_index_2": 58,
    "heRef_2": "משנה ערכין ט, ו",
    "path_2": "משנה ערכין.txt",
    "Conection Type": "commentary"
  },
  {
    "line_index_1": 248,
    "line_index_2": 58,
    "heRef_2": "משנה ערכין ט, ו",
    "path_2": "משנה ערכין.txt",
    "Conection Type": "commentary"
  },
  {
    "line_index_1": 249,
    "line_index_2": 58,
    "heRef_2": "משנה ערכין ט, ו",
    "path_2": "משנה ערכין.txt",
    "Conection Type": "commentary"
  },
  {
    "line_index_1": 250,
    "line_index_2": 58,
    "heRef_2": "משנה ערכין ט, ו",
    "path_2": "משנה ערכין.txt",
    "Conection Type": "commentary"
  },
  {
    "line_index_1": 251,
    "line_index_2": 58,
    "heRef_2": "משנה ערכין ט, ו",
    "path_2": "משנה ערכין.txt",
    "Conection Type": "commentary"
  },
  {
    "line_index_1": 252,
    "line_index_2": 58,
    "heRef_2": "משנה ערכין ט, ו",
    "path_2": "משנה ערכין.txt",
    "Conection Type": "commentary"
  },
  {
    "line_index_1": 254,
    "line_index_2": 59,
    "heRef_2": "משנה ערכין ט, ז",
    "path_2": "משנה ערכין.txt",
    "Conection Type": "commentary"
  },
  {
    "line_index_1": 255,
    "line_index_2": 59,
    "heRef_2": "משנה ערכין ט, ז",
    "path_2": "משנה ערכין.txt",
    "Conection Type": "commentary"
  },
  {
    "line_index_1": 257,
    "line_index_2": 60,
    "heRef_2": "משנה ערכין ט, ח",
    "path_2": "משנה ערכין.txt",
    "Conection Type": "commentary"
  },
  {
    "line_index_1": 258,
    "line_index_2": 60,
    "heRef_2": "משנה ערכין ט, ח",
    "path_2": "משנה ערכין.txt",
    "Conection Type": "commentary"
  },
  {
    "line_index_1": 259,
    "line_index_2": 60,
    "heRef_2": "משנה ערכין ט, ח",
    "path_2": "משנה ערכין.txt",
    "Conection Type": "commentary"
  },
  {
    "line_index_1": 260,
    "line_index_2": 60,
    "heRef_2": "משנה ערכין ט, ח",
    "path_2": "משנה ערכין.txt",
    "Conection Type": "commentary"
  },
  {
    "line_index_1": 261,
    "line_index_2": 60,
    "heRef_2": "משנה ערכין ט, ח",
    "path_2": "משנה ערכין.txt",
    "Conection Type": "commentary"
  },
  {
    "line_index_1": 261,
    "line_index_2": 860,
    "heRef_2": "ראש השנה כט., יג",
    "path_2": "ראש השנה.txt",
    "Conection Type": ""
  },
  {
    "line_index_1": 262,
    "line_index_2": 60,
    "heRef_2": "משנה ערכין ט, ח",
    "path_2": "משנה ערכין.txt",
    "Conection Type": "commentary"
  },
  {
    "line_index_1": 263,
    "line_index_2": 60,
    "heRef_2": "משנה ערכין ט, ח",
    "path_2": "משנה ערכין.txt",
    "Conection Type": "commentary"
  },
  {
    "line_index_1": 212,
    "line_index_2": 1607,
    "heRef_2": "חולין נד., טו",
    "path_2": "חולין.txt",
    "Conection Type": ""
  },
  {
    "line_index_1": 127,
    "line_index_2": 643,
    "heRef_2": "ערכין יח., ח",
    "path_2": "ערכין.txt",
    "Conection Type": ""
  },
  {
    "line_index_1": 145,
    "line_index_2": 2391,
    "heRef_2": "בבא בתרא קב.,  א",
    "path_2": "בבא בתרא.txt",
    "Conection Type": ""
  },
  {
    "line_index_1": 146,
    "line_index_2": 2391,
    "heRef_2": "בבא בתרא קב.,  א",
    "path_2": "בבא בתרא.txt",
    "Conection Type": ""
  },
  {
    "line_index_1": 145,
    "line_index_2": 2406,
    "heRef_2": "בבא בתרא קב:, ט",
    "path_2": "בבא בתרא.txt",
    "Conection Type": ""
  },
  {
    "line_index_1": 146,
    "line_index_2": 2406,
    "heRef_2": "בבא בתרא קב:, ט",
    "path_2": "בבא בתרא.txt",
    "Conection Type": ""
  },
  {
    "line_index_1": 130,
    "line_index_2": 3525,
    "heRef_2": "בבא בתרא קנא:,  א",
    "path_2": "בבא בתרא.txt",
    "Conection Type": ""
  },
  {
    "line_index_1": 259,
    "line_index_2": 665,
    "heRef_2": "בבא בתרא כד.,  א",
    "path_2": "בבא בתרא.txt",
    "Conection Type": ""
  },
  {
    "line_index_1": 259,
    "line_index_2": 684,
    "heRef_2": "בבא בתרא כד:, ה",
    "path_2": "בבא בתרא.txt",
    "Conection Type": ""
  },
  {
    "line_index_1": 105,
    "line_index_2": 1169,
    "heRef_2": "בבא בתרא מח.,  א",
    "path_2": "בבא בתרא.txt",
    "Conection Type": ""
  },
  {
    "line_index_1": 108,
    "line_index_2": 1169,
    "heRef_2": "בבא בתרא מח.,  א",
    "path_2": "בבא בתרא.txt",
    "Conection Type": ""
  },
  {
    "line_index_1": 105,
    "line_index_2": 3838,
    "heRef_2": "בבא קמא קב.,  א",
    "path_2": "בבא קמא.txt",
    "Conection Type": ""
  },
  {
    "line_index_1": 130,
    "line_index_2": 3838,
    "heRef_2": "בבא קמא קב.,  א",
    "path_2": "בבא קמא.txt",
    "Conection Type": ""
  },
  {
    "line_index_1": 134,
    "line_index_2": 3838,
    "heRef_2": "בבא קמא קב.,  א",
    "path_2": "בבא קמא.txt",
    "Conection Type": ""
  },
  {
    "line_index_1": 155,
    "line_index_2": 4098,
    "heRef_2": "בבא קמא קט:, יב",
    "path_2": "בבא קמא.txt",
    "Conection Type": ""
  },
  {
    "line_index_1": 105,
    "line_index_2": 1530,
    "heRef_2": "בבא קמא מ.,  א",
    "path_2": "בבא קמא.txt",
    "Conection Type": ""
  },
  {
    "line_index_1": 7,
    "line_index_2": 3248,
    "heRef_2": "בבא קמא פה:,  א",
    "path_2": "בבא קמא.txt",
    "Conection Type": ""
  },
  {
    "line_index_1": 219,
    "line_index_2": 3490,
    "heRef_2": "בבא מציעא קו., ח",
    "path_2": "בבא מציעא.txt",
    "Conection Type": ""
  },
  {
    "line_index_1": 148,
    "line_index_2": 3499,
    "heRef_2": "בבא מציעא קו:,  א",
    "path_2": "בבא מציעא.txt",
    "Conection Type": ""
  },
  {
    "line_index_1": 112,
    "line_index_2": 3551,
    "heRef_2": "בבא מציעא קח.,  א",
    "path_2": "בבא מציעא.txt",
    "Conection Type": ""
  },
  {
    "line_index_1": 182,
    "line_index_2": 1766,
    "heRef_2": "בבא מציעא נג:, יא",
    "path_2": "בבא מציעא.txt",
    "Conection Type": ""
  },
  {
    "line_index_1": 185,
    "line_index_2": 1768,
    "heRef_2": "בבא מציעא נד.,  א",
    "path_2": "בבא מציעא.txt",
    "Conection Type": ""
  },
  {
    "line_index_1": 232,
    "line_index_2": 2065,
    "heRef_2": "בבא מציעא סג:,  א",
    "path_2": "בבא מציעא.txt",
    "Conection Type": ""
  }
]